falco_toolbox/__about__.py
falco_toolbox/__init__.py
falco_toolbox/conf.py
falco_toolbox/htmx.py
falco_toolbox/models.py
falco_toolbox/pagination.py
falco_toolbox/sentry.py
falco_toolbox/types.py
falco_toolbox/views.py
falco_toolbox/management/commands/__init__.py
falco_toolbox/management/commands/copy_template.py
falco_toolbox/management/commands/list_templates.py
falco_toolbox-0.4.0.dist-info/METADATA
falco_toolbox-0.4.0.dist-info/WHEEL
falco_toolbox-0.4.0.dist-info/licenses/LICENSE.txt
falco_toolbox-0.4.0.dist-info/RECORD
