Metadata-Version: 2.3
Name: falco-toolbox
Version: 0.4.0
Project-URL: Documentation, https://github.com/Tobi DEGNON/falco-toolbox#readme
Project-URL: Issues, https://github.com/Tobi DEGNON/falco-toolbox/issues
Project-URL: Source, https://github.com/Tobi DEGNON/falco-toolbox
Author-email: Tobi DEGNON <tobidegnon@proton.me>
License-Expression: MIT
License-File: LICENSE.txt
Classifier: Development Status :: 4 - Beta
Classifier: Programming Language :: Python
Classifier: Programming Language :: Python :: 3.8
Classifier: Programming Language :: Python :: 3.9
Classifier: Programming Language :: Python :: 3.10
Classifier: Programming Language :: Python :: 3.11
Classifier: Programming Language :: Python :: 3.12
Classifier: Programming Language :: Python :: Implementation :: CPython
Classifier: Programming Language :: Python :: Implementation :: PyPy
Requires-Python: >=3.8
